{
 "code": "GY",
 "name": "強茂期貨",
 "sid": "2481",
 "records": {
  "2026/06/23": [
   {
    "month": "202607",
    "type": "0",
    "top5_buy": 1110,
    "top5_sell": 2634,
    "top10_buy": 1497,
    "top10_sell": 3674,
    "market_oi": 4375,
    "scope": "當月"
   },
   {
    "month": "202607",
    "type": "1",
    "top5_buy": 330,
    "top5_sell": 2634,
    "top10_buy": 330,
    "top10_sell": 3674,
    "market_oi": 4375,
    "scope": "當月"
   },
   {
    "month": "999999",
    "type": "0",
    "top5_buy": 1110,
    "top5_sell": 2634,
    "top10_buy": 1497,
    "top10_sell": 3674,
    "market_oi": 4457,
    "scope": "所有契約"
   },
   {
    "month": "999999",
    "type": "1",
    "top5_buy": 330,
    "top5_sell": 2634,
    "top10_buy": 330,
    "top10_sell": 3674,
    "market_oi": 4457,
    "scope": "所有契約"
   }
  ],
  "2026/06/29": [
   {
    "month": "202607",
    "type": "0",
    "top5_buy": 999,
    "top5_sell": 3408,
    "top10_buy": 1486,
    "top10_sell": 4265,
    "market_oi": 4882,
    "scope": "當月"
   },
   {
    "month": "202607",
    "type": "1",
    "top5_buy": 409,
    "top5_sell": 3408,
    "top10_buy": 409,
    "top10_sell": 4265,
    "market_oi": 4882,
    "scope": "當月"
   },
   {
    "month": "999999",
    "type": "0",
    "top5_buy": 1025,
    "top5_sell": 3408,
    "top10_buy": 1512,
    "top10_sell": 4325,
    "market_oi": 5066,
    "scope": "所有契約"
   },
   {
    "month": "999999",
    "type": "1",
    "top5_buy": 424,
    "top5_sell": 3408,
    "top10_buy": 424,
    "top10_sell": 4325,
    "market_oi": 5066,
    "scope": "所有契約"
   }
  ],
  "2026/06/30": [
   {
    "month": "202607",
    "type": "0",
    "top5_buy": 914,
    "top5_sell": 3398,
    "top10_buy": 1361,
    "top10_sell": 4397,
    "market_oi": 5121,
    "scope": "當月"
   },
   {
    "month": "202607",
    "type": "1",
    "top5_buy": 344,
    "top5_sell": 3398,
    "top10_buy": 344,
    "top10_sell": 4397,
    "market_oi": 5121,
    "scope": "當月"
   },
   {
    "month": "999999",
    "type": "0",
    "top5_buy": 940,
    "top5_sell": 3499,
    "top10_buy": 1387,
    "top10_sell": 4500,
    "market_oi": 5310,
    "scope": "所有契約"
   },
   {
    "month": "999999",
    "type": "1",
    "top5_buy": 359,
    "top5_sell": 3499,
    "top10_buy": 359,
    "top10_sell": 4500,
    "market_oi": 5310,
    "scope": "所有契約"
   }
  ],
  "2026/07/02": [
   {
    "month": "202607",
    "type": "0",
    "top5_buy": 859,
    "top5_sell": 3462,
    "top10_buy": 1423,
    "top10_sell": 4699,
    "market_oi": 6461,
    "scope": "當月"
   },
   {
    "month": "202607",
    "type": "1",
    "top5_buy": 274,
    "top5_sell": 3462,
    "top10_buy": 274,
    "top10_sell": 4528,
    "market_oi": 6461,
    "scope": "當月"
   },
   {
    "month": "999999",
    "type": "0",
    "top5_buy": 890,
    "top5_sell": 3563,
    "top10_buy": 1454,
    "top10_sell": 4804,
    "market_oi": 6701,
    "scope": "所有契約"
   },
   {
    "month": "999999",
    "type": "1",
    "top5_buy": 293,
    "top5_sell": 3563,
    "top10_buy": 293,
    "top10_sell": 4633,
    "market_oi": 6701,
    "scope": "所有契約"
   }
  ],
  "2026/07/03": [
   {
    "month": "202607",
    "type": "0",
    "top5_buy": 1169,
    "top5_sell": 3585,
    "top10_buy": 1739,
    "top10_sell": 4915,
    "market_oi": 6603,
    "scope": "當月"
   },
   {
    "month": "202607",
    "type": "1",
    "top5_buy": 537,
    "top5_sell": 3585,
    "top10_buy": 642,
    "top10_sell": 4712,
    "market_oi": 6603,
    "scope": "當月"
   },
   {
    "month": "999999",
    "type": "0",
    "top5_buy": 1228,
    "top5_sell": 3686,
    "top10_buy": 1798,
    "top10_sell": 5020,
    "market_oi": 6909,
    "scope": "所有契約"
   },
   {
    "month": "999999",
    "type": "1",
    "top5_buy": 576,
    "top5_sell": 3686,
    "top10_buy": 681,
    "top10_sell": 4817,
    "market_oi": 6909,
    "scope": "所有契約"
   }
  ],
  "2026/07/06": [
   {
    "month": "202607",
    "type": "0",
    "top5_buy": 1244,
    "top5_sell": 3423,
    "top10_buy": 1809,
    "top10_sell": 4803,
    "market_oi": 6833,
    "scope": "當月"
   },
   {
    "month": "202607",
    "type": "1",
    "top5_buy": 612,
    "top5_sell": 3423,
    "top10_buy": 612,
    "top10_sell": 4600,
    "market_oi": 6833,
    "scope": "當月"
   },
   {
    "month": "999999",
    "type": "0",
    "top5_buy": 1304,
    "top5_sell": 3686,
    "top10_buy": 1869,
    "top10_sell": 5070,
    "market_oi": 7298,
    "scope": "所有契約"
   },
   {
    "month": "999999",
    "type": "1",
    "top5_buy": 652,
    "top5_sell": 3686,
    "top10_buy": 652,
    "top10_sell": 4867,
    "market_oi": 7298,
    "scope": "所有契約"
   }
  ],
  "2026/07/07": [
   {
    "month": "202607",
    "type": "0",
    "top5_buy": 2144,
    "top5_sell": 3707,
    "top10_buy": 2731,
    "top10_sell": 5186,
    "market_oi": 7136,
    "scope": "當月"
   },
   {
    "month": "202607",
    "type": "1",
    "top5_buy": 1629,
    "top5_sell": 3226,
    "top10_buy": 1629,
    "top10_sell": 4705,
    "market_oi": 7136,
    "scope": "當月"
   },
   {
    "month": "999999",
    "type": "0",
    "top5_buy": 2399,
    "top5_sell": 3822,
    "top10_buy": 3020,
    "top10_sell": 5524,
    "market_oi": 8022,
    "scope": "所有契約"
   },
   {
    "month": "999999",
    "type": "1",
    "top5_buy": 1806,
    "top5_sell": 3341,
    "top10_buy": 1806,
    "top10_sell": 5043,
    "market_oi": 8022,
    "scope": "所有契約"
   }
  ],
  "2026/07/08": [
   {
    "month": "202607",
    "type": "0",
    "top5_buy": 1694,
    "top5_sell": 3405,
    "top10_buy": 2234,
    "top10_sell": 4985,
    "market_oi": 6687,
    "scope": "當月"
   },
   {
    "month": "202607",
    "type": "1",
    "top5_buy": 1032,
    "top5_sell": 2924,
    "top10_buy": 1032,
    "top10_sell": 4504,
    "market_oi": 6687,
    "scope": "當月"
   },
   {
    "month": "999999",
    "type": "0",
    "top5_buy": 1969,
    "top5_sell": 3958,
    "top10_buy": 2544,
    "top10_sell": 5567,
    "market_oi": 7826,
    "scope": "所有契約"
   },
   {
    "month": "999999",
    "type": "1",
    "top5_buy": 1221,
    "top5_sell": 3477,
    "top10_buy": 1221,
    "top10_sell": 5086,
    "market_oi": 7826,
    "scope": "所有契約"
   }
  ],
  "2026/06/24": [
   {
    "month": "202607",
    "type": "0",
    "top5_buy": 616,
    "top5_sell": 3036,
    "top10_buy": 992,
    "top10_sell": 4028,
    "market_oi": 4726,
    "scope": "當月"
   },
   {
    "month": "202607",
    "type": "1",
    "top5_buy": 106,
    "top5_sell": 2696,
    "top10_buy": 106,
    "top10_sell": 3688,
    "market_oi": 4726,
    "scope": "當月"
   },
   {
    "month": "999999",
    "type": "0",
    "top5_buy": 620,
    "top5_sell": 3036,
    "top10_buy": 996,
    "top10_sell": 4028,
    "market_oi": 4803,
    "scope": "所有契約"
   },
   {
    "month": "999999",
    "type": "1",
    "top5_buy": 110,
    "top5_sell": 2696,
    "top10_buy": 110,
    "top10_sell": 3688,
    "market_oi": 4803,
    "scope": "所有契約"
   }
  ],
  "2026/06/25": [
   {
    "month": "202607",
    "type": "0",
    "top5_buy": 692,
    "top5_sell": 3350,
    "top10_buy": 1100,
    "top10_sell": 4322,
    "market_oi": 5198,
    "scope": "當月"
   },
   {
    "month": "202607",
    "type": "1",
    "top5_buy": 96,
    "top5_sell": 2915,
    "top10_buy": 96,
    "top10_sell": 3887,
    "market_oi": 5198,
    "scope": "當月"
   },
   {
    "month": "999999",
    "type": "0",
    "top5_buy": 692,
    "top5_sell": 3350,
    "top10_buy": 1110,
    "top10_sell": 4336,
    "market_oi": 5327,
    "scope": "所有契約"
   },
   {
    "month": "999999",
    "type": "1",
    "top5_buy": 96,
    "top5_sell": 2915,
    "top10_buy": 96,
    "top10_sell": 3901,
    "market_oi": 5327,
    "scope": "所有契約"
   }
  ],
  "2026/06/26": [
   {
    "month": "202607",
    "type": "0",
    "top5_buy": 706,
    "top5_sell": 3275,
    "top10_buy": 1173,
    "top10_sell": 4109,
    "market_oi": 4714,
    "scope": "當月"
   },
   {
    "month": "202607",
    "type": "1",
    "top5_buy": 268,
    "top5_sell": 3275,
    "top10_buy": 373,
    "top10_sell": 4009,
    "market_oi": 4714,
    "scope": "當月"
   },
   {
    "month": "999999",
    "type": "0",
    "top5_buy": 717,
    "top5_sell": 3275,
    "top10_buy": 1189,
    "top10_sell": 4151,
    "market_oi": 4869,
    "scope": "所有契約"
   },
   {
    "month": "999999",
    "type": "1",
    "top5_buy": 268,
    "top5_sell": 3275,
    "top10_buy": 378,
    "top10_sell": 4151,
    "market_oi": 4869,
    "scope": "所有契約"
   }
  ],
  "2026/07/01": [
   {
    "month": "202607",
    "type": "0",
    "top5_buy": 934,
    "top5_sell": 3405,
    "top10_buy": 1413,
    "top10_sell": 4382,
    "market_oi": 5602,
    "scope": "當月"
   },
   {
    "month": "202607",
    "type": "1",
    "top5_buy": 364,
    "top5_sell": 3405,
    "top10_buy": 450,
    "top10_sell": 4382,
    "market_oi": 5602,
    "scope": "當月"
   },
   {
    "month": "999999",
    "type": "0",
    "top5_buy": 962,
    "top5_sell": 3506,
    "top10_buy": 1441,
    "top10_sell": 4495,
    "market_oi": 5827,
    "scope": "所有契約"
   },
   {
    "month": "999999",
    "type": "1",
    "top5_buy": 381,
    "top5_sell": 3506,
    "top10_buy": 467,
    "top10_sell": 4495,
    "market_oi": 5827,
    "scope": "所有契約"
   }
  ]
 }
}